sqletic/__init__.py
sqletic/__init__.py~
sqletic/engine.py
sqletic/engine.py~
sqletic/expression.py
sqletic/expression.py~
sqletic/scope.py
sqletic/scope.py~
sqletic-0.1.5.dist-info/METADATA
sqletic-0.1.5.dist-info/WHEEL
sqletic-0.1.5.dist-info/entry_points.txt
sqletic-0.1.5.dist-info/RECORD
