Metadata-Version: 2.1
Name: sqletic
Version: 0.1.5
Summary: 
Author: Charles Bajeux
Author-email: charles.bajeux@gmail.com
Requires-Python: >=3.11,<4.0
Classifier: Programming Language :: Python :: 3
Classifier: Programming Language :: Python :: 3.11
Classifier: Programming Language :: Python :: 3.12
Requires-Dist: sqlton (>=0.1.17,<0.2.0)
